pypmltracker/__init__.py
pypmltracker/setup.py
pypmltracker-0.1.3.dist-info/METADATA
pypmltracker-0.1.3.dist-info/WHEEL
pypmltracker-0.1.3.dist-info/top_level.txt
pypmltracker-0.1.3.dist-info/RECORD
