Metadata-Version: 2.4
Name: pypmltracker
Version: 0.1.3
Summary: A comprehensive ML experiment tracking library
Author-email: Suvadip Chakraborty <suvadipchakraborty2006@gmail.com>
Project-URL: Homepage, https://github.com/suvchr105/pypmltracker
Project-URL: Issues, https://github.com/suvchr105/pypmltracker/issues
Classifier: Programming Language :: Python :: 3
Classifier: License :: OSI Approved :: MIT License
Classifier: Operating System :: OS Independent
Requires-Python: >=3.6
